flexnlp/__init__.py
flexnlp/pool/__init__.py
flexnlp/pool/aggregators.py
flexnlp/utils/__init__.py
flexnlp/utils/adapters/__init__.py
flexnlp/utils/adapters/ss_adapters.py
flexnlp/utils/collators/__init__.py
flexnlp/utils/collators/classification_sampler.py
flexnlp/utils/collators/collate_functions.py
flexnlp-0.1.0.dist-info/LICENSE
flexnlp-0.1.0.dist-info/METADATA
flexnlp-0.1.0.dist-info/WHEEL
flexnlp-0.1.0.dist-info/top_level.txt
flexnlp-0.1.0.dist-info/RECORD
