Metadata-Version: 2.1
Name: flexnlp
Version: 0.1.0
Home-page: https://github.com/FLEXible-FL/flex-nlp
Author: Cristina Zuheros-Montes and Argente-Garrido Alberto
Keywords: FL federated-learning flexible NLP
Requires-Python: >=3.8.10
License-File: LICENSE
Requires-Dist: numpy
Requires-Dist: multiprocess
Requires-Dist: scikit-learn
Requires-Dist: cardinality
Requires-Dist: sultan
Requires-Dist: tqdm
Requires-Dist: scipy
Requires-Dist: gdown
Requires-Dist: flexible-fl
Requires-Dist: torch
Requires-Dist: torchtext
Requires-Dist: portalocker
Requires-Dist: torchdata
Requires-Dist: datasets
Requires-Dist: transformers
Requires-Dist: sentence-transformers
Requires-Dist: sentencepiece
Provides-Extra: develop
Requires-Dist: pytest ; extra == 'develop'
Requires-Dist: pytest-cov ; extra == 'develop'
Requires-Dist: pytest-xdist ; extra == 'develop'
Requires-Dist: coverage ; extra == 'develop'
Requires-Dist: jinja2 ; extra == 'develop'
Provides-Extra: pytorch
Requires-Dist: torch ; extra == 'pytorch'
Requires-Dist: torchvision ; extra == 'pytorch'
Requires-Dist: torchtext ; extra == 'pytorch'
Requires-Dist: torchdata ; extra == 'pytorch'
Requires-Dist: portalocker ; extra == 'pytorch'
